xss_shield/__init__.py
xss_shield-1.2.2.dist-info/METADATA
xss_shield-1.2.2.dist-info/WHEEL
xss_shield-1.2.2.dist-info/licenses/LICENSE
xss_shield-1.2.2.dist-info/RECORD
