Metadata-Version: 2.3
Name: xss-shield
Version: 1.2.2
Summary: A library used to stop your website from being attacked.
Project-URL: Homepage, https://github.com/GordonZhang2024/xss-shield/
Project-URL: Issues, https://github.com/GordonZhang2024/xss-shield/issues
Project-URL: Docs, https://xss-shield.readthedocs.io/en/latest/
Author-email: Gordon Zhang <jp20171211@163.com>
License-File: LICENSE
Keywords: attack,django,flask,shield,web,xss
Classifier: Development Status :: 5 - Production/Stable
Classifier: License :: OSI Approved :: MIT License
Classifier: Natural Language :: English
Classifier: Operating System :: OS Independent
Classifier: Programming Language :: Python :: 3
Classifier: Topic :: Internet
Classifier: Topic :: Software Development :: Libraries :: Python Modules
Requires-Python: >=3.8
